takeshi/__init__.py
takeshi/config.py
takeshi/version.py
takeshi-0.0.2.dist-info/LICENSE
takeshi-0.0.2.dist-info/METADATA
takeshi-0.0.2.dist-info/WHEEL
takeshi-0.0.2.dist-info/top_level.txt
takeshi-0.0.2.dist-info/RECORD
