Metadata-Version: 2.1
Name: takeshi
Version: 0.0.2
Summary: Robust Background Processing
Home-page: https://github.com/orklann/takeshi
Author: Aaron Elkins
Author-email: threcius@yahoo.com
License: GPLv2.0
Platform: any
License-File: LICENSE
